sharefiles/__init__.py
sharefiles/__main__.py
sharefiles/command_line.py
sharefiles-0.0.1.dist-info/LICENCE
sharefiles-0.0.1.dist-info/METADATA
sharefiles-0.0.1.dist-info/WHEEL
sharefiles-0.0.1.dist-info/entry_points.txt
sharefiles-0.0.1.dist-info/top_level.txt
sharefiles-0.0.1.dist-info/RECORD
