Metadata-Version: 2.1
Name: sharefiles
Version: 0.0.1
Summary: Opens an HTTP server quickly at the script location where can download and upload files.
Home-page: https://github.com/deduble/sharefiles
Author: deduble
Author-email: Yunus Kayalidere <yunus.kayalidere@gmail.com>
Project-URL: Homepage, https://github.com/deduble/sharefiles
Project-URL: Bug Tracker, https://github.com/pypa/deduble/sharefiles
Classifier: Programming Language :: Python :: 3
Classifier: License :: OSI Approved :: MIT License
Classifier: Operating System :: OS Independent
Requires-Python: >=3.2
License-File: LICENCE
